README.md
setup.py
patul/__init__.py
patul/crawler.py
patul/request.py
patul/response.py
patul/spider.py
patul.egg-info/PKG-INFO
patul.egg-info/SOURCES.txt
patul.egg-info/dependency_links.txt
patul.egg-info/requires.txt
patul.egg-info/top_level.txt
test/__init__.py
test/spider.py